signal_ICT_Trupalijasani_92510133011/__init__.py
signal_ICT_Trupalijasani_92510133011/operations.py
signal_ICT_Trupalijasani_92510133011/trigonometric_signals.py
signal_ICT_Trupalijasani_92510133011/unitary_signals.py
signal_ICT_Trupalijasani_92510133011-0.1.dist-info/METADATA
signal_ICT_Trupalijasani_92510133011-0.1.dist-info/WHEEL
signal_ICT_Trupalijasani_92510133011-0.1.dist-info/top_level.txt
signal_ICT_Trupalijasani_92510133011-0.1.dist-info/RECORD
