Metadata-Version: 2.1
Name: signal-ICT-Trupalijasani-92510133011
Version: 0.1
Summary: Educational signals package for Signals & Systems assignment
Author: Trupalijasani
Author-email: student@example.com
Requires-Python: >=3.8
Requires-Dist: numpy
Requires-Dist: matplotlib
